pypi_info/__init__.py
pypi_info/__main__.py
pypi_info/__version__.py
pypi_info/custom_logging.py
pypi_info/gui_qt5.py
pypi_info/loading.gif
pypi_info/pipinfo.py
pypi_info-0.61.5.dist-info/METADATA
pypi_info-0.61.5.dist-info/WHEEL
pypi_info-0.61.5.dist-info/entry_points.txt
pypi_info-0.61.5.dist-info/top_level.txt
pypi_info-0.61.5.dist-info/RECORD
